camelot/__init__.py
camelot/__main__.py
camelot/__version__.py
camelot/backends/__init__.py
camelot/backends/base.py
camelot/backends/ghostscript_backend.py
camelot/backends/image_conversion.py
camelot/backends/pdfium_backend.py
camelot/backends/poppler_backend.py
camelot/cli.py
camelot/core.py
camelot/handlers.py
camelot/image_processing.py
camelot/io.py
camelot/parsers/__init__.py
camelot/parsers/base.py
camelot/parsers/hybrid.py
camelot/parsers/lattice.py
camelot/parsers/network.py
camelot/parsers/stream.py
camelot/plotting.py
camelot/py.typed
camelot/utils.py
pypdf_table_extraction/__init__.py
pypdf_table_extraction/__main__.py
pypdf_table_extraction/__version__.py
pypdf_table_extraction/backends/__init__.py
pypdf_table_extraction/backends/ghostscript_backend.py
pypdf_table_extraction/backends/image_conversion.py
pypdf_table_extraction/backends/pdfium_backend.py
pypdf_table_extraction/backends/poppler_backend.py
pypdf_table_extraction/cli.py
pypdf_table_extraction/core.py
pypdf_table_extraction/handlers.py
pypdf_table_extraction/image_processing.py
pypdf_table_extraction/io.py
pypdf_table_extraction/parsers/__init__.py
pypdf_table_extraction/parsers/base.py
pypdf_table_extraction/parsers/lattice.py
pypdf_table_extraction/parsers/stream.py
pypdf_table_extraction/plotting.py
pypdf_table_extraction/py.typed
pypdf_table_extraction/utils.py
pypdf_table_extraction-1.0.2.dist-info/LICENSE
pypdf_table_extraction-1.0.2.dist-info/METADATA
pypdf_table_extraction-1.0.2.dist-info/WHEEL
pypdf_table_extraction-1.0.2.dist-info/entry_points.txt
pypdf_table_extraction-1.0.2.dist-info/RECORD
