Metadata-Version: 2.3
Name: pypdf_table_extraction
Version: 1.0.2
Summary: DEPRECATED - Please use camelot-py instead.
License: MIT
Author: Vinayak Mehta
Author-email: vmehta94@gmail.com
Requires-Python: >=3.8,<4.0
Classifier: Development Status :: 5 - Production/Stable
Classifier: License :: OSI Approved :: MIT License
Classifier: Programming Language :: Python :: 3
Classifier: Programming Language :: Python :: 3.8
Classifier: Programming Language :: Python :: 3.9
Classifier: Programming Language :: Python :: 3.10
Classifier: Programming Language :: Python :: 3.11
Classifier: Programming Language :: Python :: 3.12
Classifier: Programming Language :: Python :: 3.13
Requires-Dist: chardet (>=5.1.0,<6.0.0)
Requires-Dist: click (>=8.0.1)
Requires-Dist: numpy (>=1.24.4,<2.0.0) ; python_version >= "3.8" and python_version < "3.12"
Requires-Dist: numpy (>=1.26.1) ; python_version >= "3.12"
Requires-Dist: openpyxl (>=3.1.0,<4.0.0)
Requires-Dist: pandas (>=1.5.3,<2.0.0) ; python_version >= "3.8" and python_version < "3.10"
Requires-Dist: pandas (>=2.2.2,<3.0.0) ; python_version >= "3.10"
Requires-Dist: pdfminer-six (>=20240706,<20240707)
Requires-Dist: pypdf (>=3.17,<4.0) ; python_version >= "3.8" and python_version < "3.12"
Requires-Dist: pypdf (>=4.0,<6.0) ; python_version >= "3.12"
Requires-Dist: tabulate (>=0.9.0,<0.10.0)
Requires-Dist: typing-extensions (>=4.12.2,<5.0.0) ; python_version >= "3.8" and python_version < "3.11"
Project-URL: Changelog, https://github.com/py-pdf/pypdf_table_extraction/releases
Project-URL: Documentation, https://pypdf-table-extraction.readthedocs.io/
Project-URL: Homepage, https://github.com/py-pdf/pypdf_table_extraction
Project-URL: Repository, https://github.com/py-pdf/pypdf_table_extraction
